mugmoment/__init__.py
mugmoment/bttv_api.py
mugmoment/converters.py
mugmoment/twitch_api.py
mugmoment-0.2.2.dist-info/WHEEL
mugmoment-0.2.2.dist-info/METADATA
mugmoment-0.2.2.dist-info/RECORD
