Metadata-Version: 2.1
Name: mugmoment
Version: 0.2.2
Summary: Library to download chat logs from twitch VODs
Home-page: https://gitlab.com/a/mugmoment
License: MIT
Author: Ave
Author-email: ave@ave.zone
Requires-Python: >=3.6,<4.0
Classifier: License :: OSI Approved :: MIT License
Classifier: Programming Language :: Python :: 3
Classifier: Programming Language :: Python :: 3.6
Classifier: Programming Language :: Python :: 3.7
Classifier: Programming Language :: Python :: 3.8
Classifier: Programming Language :: Python :: 3.9
Requires-Dist: httpx (>=0.17.1,<0.18.0)
Project-URL: Repository, https://gitlab.com/a/mugmoment
